jconfig/__init__.py
jconfig/base.py
jconfig/jconfig.py
jconfig/memory.py
vk_mda/__init__.py
vk_mda/audio.py
vk_mda/audio_url_decoder.py
vk_mda/bot_longpoll.py
vk_mda/enums.py
vk_mda/exceptions.py
vk_mda/execute.py
vk_mda/keyboard.py
vk_mda/longpoll.py
vk_mda/requests_pool.py
vk_mda/streaming.py
vk_mda/tools.py
vk_mda/upload.py
vk_mda/utils.py
vk_mda/vk_api.py
vk_mda-11.9.3.dist-info/LICENSE
vk_mda-11.9.3.dist-info/METADATA
vk_mda-11.9.3.dist-info/WHEEL
vk_mda-11.9.3.dist-info/top_level.txt
vk_mda-11.9.3.dist-info/RECORD
