Metadata-Version: 2.1
Name: vk-mda
Version: 11.9.3
Summary: Python модуль для написания скриптов для социальной сети Вконтакте (vk.com) (API wrapper)
Home-page: https://github.com/lionead/vk_mda
Author: lionead
Author-email: lionia058@gmail.com
License: Apache License, Version 2.0, see LICENSE file
Download-URL: https://github.com/lionead/vk_mda/archive/master.zip
Platform: UNKNOWN
Classifier: License :: OSI Approved :: Apache Software License
Classifier: Operating System :: OS Independent
Classifier: Programming Language :: Python
Classifier: Programming Language :: Python :: 2
Classifier: Programming Language :: Python :: 2.7
Classifier: Programming Language :: Python :: 3
Classifier: Programming Language :: Python :: 3.4
Classifier: Programming Language :: Python :: 3.5
Classifier: Programming Language :: Python :: 3.6
Classifier: Programming Language :: Python :: 3.7
Classifier: Programming Language :: Python :: Implementation :: PyPy
Classifier: Programming Language :: Python :: Implementation :: CPython
Requires-Dist: requests
Requires-Dist: six
Requires-Dist: enum34 ; python_version < "3.4"
Provides-Extra: vkaudio
Requires-Dist: beautifulsoup4 ; extra == 'vkaudio'
Provides-Extra: vkstreaming
Requires-Dist: websocket-client ; extra == 'vkstreaming'
